reading_impact_model/__init__.py
reading_impact_model/impact_model.py
reading_impact_model/matchers/__init__.py
reading_impact_model/matchers/alpino_matcher.py
reading_impact_model/matchers/alpinor_matcher_old.py
reading_impact_model/matchers/matcher.py
reading_impact_model/matchers/nltk_matcher.py
reading_impact_model/matchers/spacy_matcher.py
reading_impact_model/matchers/stanza_matcher.py
reading_impact_model/matchers/trankit_matcher.py
reading_impact_model/model/__init__.py
reading_impact_model/model/phrase.py
reading_impact_model/models/__init__.py
reading_impact_model/models/impact_model-en-0.1.pcl
reading_impact_model/models/impact_model-en-0.2.pcl
reading_impact_model/models/impact_model-en-0.3.pcl
reading_impact_model/models/impact_model-en-0.4.pcl
reading_impact_model/models/impact_model-en-0.5.pcl
reading_impact_model/models/impact_model-en-0.6.json
reading_impact_model/models/impact_model-en-0.6.pcl
reading_impact_model/models/impact_model-en-0.7.json
reading_impact_model/models/impact_model-en-0.7.pcl
reading_impact_model/models/impact_model-en.json
reading_impact_model/models/impact_model-en.pcl
reading_impact_model/models/impact_model-nl-1.0.json
reading_impact_model/models/impact_model-nl.json
reading_impact_model/models/impact_model-nl.pcl
reading_impact_model/models/impact_model_en.py
reading_impact_model/models/impact_model_nl.py
reading_impact_model/reading_impact.py
reading_impact_model-1.0.3.dist-info/METADATA
reading_impact_model-1.0.3.dist-info/WHEEL
reading_impact_model-1.0.3.dist-info/RECORD
