Metadata-Version: 2.1
Name: reading-impact-model
Version: 1.0.3
Summary: 
Home-page: https://github.com/marijnkoolen/reading-impact-model
License: MIT
Author: Marijn Koolen
Author-email: marijn.koolen@gmail.com
Requires-Python: >=3.10,<4.0
Classifier: Development Status :: 4 - Beta
Classifier: Intended Audience :: Science/Research
Classifier: License :: OSI Approved :: MIT License
Classifier: Operating System :: OS Independent
Classifier: Programming Language :: Python :: 3
Classifier: Programming Language :: Python :: 3.10
Classifier: Programming Language :: Python :: 3.11
Classifier: Topic :: Scientific/Engineering
Requires-Dist: nltk (>=3.8.1,<4.0.0)
Requires-Dist: pytest (>=7.2.2,<8.0.0)
Requires-Dist: xmltodict (>=0.13.0,<0.14.0)
Project-URL: Repository, https://github.com/marijnkoolen/reading-impact-model
